cegalprizm/pythontool/__init__.py
cegalprizm/pythontool/_config.py
cegalprizm/pythontool/_docstring_utils.py
cegalprizm/pythontool/_utils.py
cegalprizm/pythontool/_well_known_object_description.py
cegalprizm/pythontool/borehole.py
cegalprizm/pythontool/checkshot.py
cegalprizm/pythontool/chunk.py
cegalprizm/pythontool/chunking_array.py
cegalprizm/pythontool/chunktype.py
cegalprizm/pythontool/completions_casingstring.py
cegalprizm/pythontool/completions_perforation.py
cegalprizm/pythontool/completions_plugback.py
cegalprizm/pythontool/completions_squeeze.py
cegalprizm/pythontool/completionsset.py
cegalprizm/pythontool/deletion.py
cegalprizm/pythontool/enums.py
cegalprizm/pythontool/exceptions.py
cegalprizm/pythontool/experimental.py
cegalprizm/pythontool/faultinterpretation.py
cegalprizm/pythontool/folder.py
cegalprizm/pythontool/globalwelllogfolder.py
cegalprizm/pythontool/grid.py
cegalprizm/pythontool/gridproperty.py
cegalprizm/pythontool/gridpropertycollection.py
cegalprizm/pythontool/horizoninterpretation.py
cegalprizm/pythontool/horizoninterpretationutils.py
cegalprizm/pythontool/interpretationfolder.py
cegalprizm/pythontool/markerattribute.py
cegalprizm/pythontool/markercollection.py
cegalprizm/pythontool/markerstratigraphy.py
cegalprizm/pythontool/observeddata.py
cegalprizm/pythontool/parameter_validation.py
cegalprizm/pythontool/petrelconnection.py
cegalprizm/pythontool/petrellink.py
cegalprizm/pythontool/petrelobject.py
cegalprizm/pythontool/points.py
cegalprizm/pythontool/polylineattribute.py
cegalprizm/pythontool/polylines.py
cegalprizm/pythontool/primitives.py
cegalprizm/pythontool/savedsearch.py
cegalprizm/pythontool/segment.py
cegalprizm/pythontool/seismic.py
cegalprizm/pythontool/stratigraphyzone.py
cegalprizm/pythontool/surface.py
cegalprizm/pythontool/template.py
cegalprizm/pythontool/transactions.py
cegalprizm/pythontool/vertices.py
cegalprizm/pythontool/wavelet.py
cegalprizm/pythontool/wellattribute.py
cegalprizm/pythontool/wellfolder.py
cegalprizm_pythontoolpro-2.8.0.dist-info/METADATA
cegalprizm_pythontoolpro-2.8.0.dist-info/WHEEL
cegalprizm_pythontoolpro-2.8.0.dist-info/top_level.txt
cegalprizm_pythontoolpro-2.8.0.dist-info/RECORD
