Metadata-Version: 2.1
Name: cegalprizm-pythontoolpro
Version: 2.8.0
Summary: Python API for interfacing with Petrel
Home-page: 
Author: 
Author-email: 
Classifier: Programming Language :: Python :: 3
Classifier: Operating System :: OS Independent
Classifier: License :: Other/Proprietary License
Requires-Python: >=3.6
Requires-Dist: grpcio >=1.33.2
Requires-Dist: protobuf
Requires-Dist: numpy
Requires-Dist: pandas
Requires-Dist: requests
Requires-Dist: cegalprizm-hub <2,>=1.2.4
Requires-Dist: cryptography ==41.0.7 ; python_full_version == "3.9.0"
Requires-Dist: cryptography ==41.0.7 ; python_full_version == "3.9.1"
Requires-Dist: setuptools <=80.8.0 ; python_version < "3.12"
Requires-Dist: setuptools <=80.8.0,>=66.1.0 ; python_version >= "3.12"
